orator_validator.py
orator_validator-0.4.1.data/scripts/orator_validator.py
orator_validator-0.4.1.dist-info/LICENSE
orator_validator-0.4.1.dist-info/METADATA
orator_validator-0.4.1.dist-info/WHEEL
orator_validator-0.4.1.dist-info/top_level.txt
orator_validator-0.4.1.dist-info/RECORD
