Metadata-Version: 2.1
Name: orator-validator
Version: 0.4.1
Summary: Orator Validator provides the best Model implement validation for Orator
Home-page: https://pypi.org/project/orator-validator/
Author: Alfonso Villalobos
Author-email: alfonso@codepeat.com
License: MIT
Platform: UNKNOWN
Classifier: Programming Language :: Python :: 3.7
Classifier: License :: OSI Approved :: MIT License
Classifier: Operating System :: OS Independent
Requires-Python: >=3.7
